{
  "name": "django-email-learning",
  "version": "0.2.43",
  "summary": "A platform for creating and delivering  learning materials via email within a Django application. It provides tools for content management, user role-based administration, and scheduler integration for automated content delivery.",
  "author": "Payam Najafizadeh",
  "license": null,
  "home_page": "https://github.com/AvaCodeSolutions/django-email-learning",
  "download_filename": "django_email_learning-0.2.43.tar.gz",
  "download_time": "2026-04-04T08:26:26.794737",
  "package_url": "https://pypi.org/project/django-email-learning/"
}